cmem_plugin_yaml/__init__.py
cmem_plugin_yaml/logo.svg
cmem_plugin_yaml/parse.py
cmem_plugin_yaml-1.0.1.dist-info/METADATA
cmem_plugin_yaml-1.0.1.dist-info/WHEEL
cmem_plugin_yaml-1.0.1.dist-info/licenses/LICENSE
cmem_plugin_yaml-1.0.1.dist-info/RECORD
